hrai_python/__init__.py
hrai_python/hrai_logger.py
hrai_python/hrai_utils.py
hrai_python/tests/__init__.py
hrai_python/tests/tests.py
hrai_python-0.3.5.dist-info/METADATA
hrai_python-0.3.5.dist-info/WHEEL
hrai_python-0.3.5.dist-info/RECORD
