Metadata-Version: 2.1
Name: hrai_python
Version: 0.3.5
Summary: A decorator for logging OpenAI API requests and responses.
License: Apache-2.0
Author: Quoc Duong
Author-email: qduong@humanreadable.ai
Maintainer: Michael Keels
Maintainer-email: mkeels@humanreadable.ai
Requires-Python: >=3.9
Classifier: License :: OSI Approved :: Apache Software License
Classifier: Programming Language :: Python :: 3
Classifier: Programming Language :: Python :: 3.9
Classifier: Programming Language :: Python :: 3.10
Classifier: Programming Language :: Python :: 3.11
Classifier: Programming Language :: Python :: 3.12
Classifier: Programming Language :: Python :: 3.13
Requires-Dist: httpx (>=0.27.2,<0.28.0)
Requires-Dist: openai (>=1.40.3,<2.0.0)
Requires-Dist: requests (>=2.26.0,<3.0.0)
